<configs>
	<append xpath="/blocks">

<block name="GlideMaster">
	<property name="CreativeMode" value="None"/>
	<property name="CustomIconTint" value="240,230,140"/>
	<property name="Material" value="SuperGlide"/>
	<property name="Texture" value="320"/>
	<property name="Path" value="solid"/>
	<property name="Stacknumber" value="20000"/>
	<property name="SellableToTrader" value="false"/>
	<property name="NoScrapping" value="true"/>
	<property name="StabilityFull" value="true"/>
	<property class="RepairItems">
		<property name="dbVariantHelper" value="1"/>
	</property>
	<drop event="Destroy" count="0"/>
	<drop event="Fall" count="0" prob="0"/>
	<property name="DescriptionKey" value="dbDesc"/>
	<property name="PickupJournalEntry" value="dungeonBlocksTip"/>
	<property name="DisplayType" value="blockHardened"/>
	<property name="FilterTags" value="fdesign"/>
	<property name="SortOrder1" value="40l0"/>
	<property name="SortOrder2" value="1337"/>
	<property name="Group" value="Building"/>
</block>


<block name="GlideBlock">
	<property name="Extends" value="GlideMaster"/>
	<property name="CreativeMode" value="Dev"/>
	<property name="CustomIcon" value="woodBlock"/>
	<property name="Shape" value="New"/>
	<property name="Model" value="Cube"/>
	<property name="SortOrder2" value="0050"/> 
</block>


<block name="GlideHalf">
	<property name="Extends" value="GlideMaster"/>
	<property name="CreativeMode" value="Dev"/>
	<property name="CustomIcon" value="woodHalf"/>
	<property name="Shape" value="New"/>
	<property name="Model" value="cube_half"/>
	<property name="SortOrder2" value="0060"/> 
</block>

<block name="GlideQuarter">
	<property name="Extends" value="GlideMaster"/>
	<property name="CustomIcon" value="woodQuarter"/>
	<property name="CreativeMode" value="Dev"/>
	<property name="Shape" value="New"/>
	<property name="Model" value="cube_quarter"/>
	<property name="Collide" value="movement,melee,bullet,arrow,rocket"/>
	<property name="LightOpacity" value="0"/>
	<property name="SortOrder2" value="0070"/> 
</block>

<block name="GlideQuarterCNR">
	<property name="Extends" value="GlideMaster"/>
	<property name="CustomIcon" value="woodQuarterCNR"/>
	<property name="CreativeMode" value="Dev"/>
	<property name="Shape" value="New"/>
	<property name="Model" value="quarter_inside_corner"/>
	<property name="SortOrder2" value="0080"/> 
</block>

<block name="GlideQuarterTeeSCtr">
	<property name="Extends" value="GlideMaster"/>
	<property name="CustomIcon" value="woodQuarterTeeSCtr"/>
	<property name="CreativeMode" value="Dev"/>
	<property name="Shape" value="New"/>
	<property name="Model" value="quarter_t_centered"/>
	<property name="Place" value="TowardsPlacerInverted"/>
	<property name="SortOrder2" value="0110"/> 
</block>

<block name="GlideQuarterSCtr">
	<property name="Extends" value="GlideMaster"/>
	<property name="CustomIcon" value="woodQuarterSCtr"/>
	<property name="CreativeMode" value="Dev"/>
	<property name="Shape" value="New"/>
	<property name="Model" value="quarter_centered_wall"/>
	<property name="Place" value="TowardsPlacerInverted"/>
	<property name="UseGlobalUV" value="Global"/>
	<property name="Collide" value="movement,melee,bullet,arrow,rocket"/>
	<property name="SortOrder2" value="0110"/> 
</block>

<block name="GlideQuarterCNR3Way">
	<property name="Extends" value="GlideMaster"/>
	<property name="CustomIcon" value="woodQuarterCNR3Way"/>
	<property name="CreativeMode" value="Dev"/>
	<property name="Shape" value="New"/>
	<property name="Model" value="quarter_inside_corner_3way"/>
	<property name="SortOrder2" value="0090"/> 
</block>


<block name="GlideRamp">
	<property name="Extends" value="GlideMaster"/>
	<property name="CustomIcon" value="woodRamp"/>
	<property name="CreativeMode" value="Dev"/>
	<property name="Shape" value="New"/>
	<property name="Model" value="ramp"/>
	<property name="Place" value="TowardsPlacerInverted"/>
	<property name="Collide" value="movement,melee,bullet,arrow,rocket"/>
	<property name="SortOrder2" value="0200"/> 
</block>




<block name="GlideStairsFilledRailingLeft">
	<property name="Extends" value="GlideMaster"/>
	<property name="CustomIcon" value="woodStairsFilledRailingLeft"/>
	<property name="CreativeMode" value="Dev"/>
	<property name="Shape" value="New"/>
	<property name="Model" value="Stairs_filled_railing_left"/>
	<property name="Place" value="TowardsPlacerInverted"/>
	<property name="MultiBlockDim" value="1,2,1"/>
	<property name="UseGlobalUV" value="L,D,D,D,L,D"/> 
	<property name="Stairs"/>
	<property name="ImposterExchange" value="imposterRamp" param1="2"/>
	<property name="MirrorSibling" value="GlideStairsFilledRailingRight"/>
	<property name="SortOrder2" value="0540"/> 
</block>

<block name="GlideStairsFilledRailingRight">
	<property name="Extends" value="GlideMaster"/>
	<property name="CustomIcon" value="woodStairsFilledRailingRight"/>
	<property name="CreativeMode" value="Dev"/>
	<property name="Shape" value="New"/>
	<property name="Model" value="Stairs_filled_railing_right"/>
	<property name="Place" value="TowardsPlacerInverted"/>
	<property name="MultiBlockDim" value="1,2,1"/>
	<property name="UseGlobalUV" value="L,D,D,D,L,D"/> 
	<property name="Stairs"/>
	<property name="ImposterExchange" value="imposterRamp" param1="2"/>
	<property name="MirrorSibling" value="GlideStairsFilledRailingLeft"/>
	<property name="SortOrder2" value="0550"/> 
</block>

<block name="GlidePlate">
	<property name="Extends" value="GlideMaster"/>
	<property name="CustomIcon" value="woodPlate"/>
	<property name="CreativeMode" value="Dev"/>
	<property name="Shape" value="New"/>
	<property name="Model" value="Plate"/>
	<property name="SortOrder2" value="0150"/> 
</block>

<block name="GlidePlateOffset">
	<property name="Extends" value="GlideMaster"/>
	<property name="CustomIcon" value="woodPlateOffset"/>
	<property name="CreativeMode" value="Dev"/>
	<property name="Shape" value="New"/>
	<property name="Model" value="tube_center_straight"/>
	<property name="SortOrder2" value="0171"/> 
</block>

<block name="GlideCatwalk">
	<property name="Extends" value="GlideMaster"/>
	<property name="CustomIcon" value="woodCatwalk"/>
	<property name="CreativeMode" value="Dev"/>
	<property name="Shape" value="New"/>
	<property name="Model" value="catwalk"/>
	<property name="LightOpacity" value="6"/>
	<property name="ImposterExchange" value="imposterPlate" param1="67"/>
	<property name="UseGlobalUV" value="Local"/>
	<property name="SortOrder2" value="0640"/>  
</block>

<block name="GlideCatwalkRailing2">
	<property name="Extends" value="GlideMaster"/>
	<property name="CustomIcon" value="woodCatwalkRailing2"/>
	<property name="CreativeMode" value="Dev"/>
	<property name="Model" value="catwalk_rail"/>
	<property name="SortOrder2" value="0650"/>  
</block>

<block name="GlideCatwalkRailing1">
	<property name="Extends" value="GlideMaster"/>
	<property name="CustomIcon" value="woodCatwalkRailing1"/>
	<property name="CreativeMode" value="Dev"/>
	<property name="Model" value="catwalk_rail_single"/>
	<property name="SortOrder2" value="0650"/>  
</block>

<block name="GlideRailing">
	<property name="Extends" value="GlideMaster"/>
	<property name="CustomIcon" value="woodRailing"/>
	<property name="CreativeMode" value="Dev"/>
	<property name="Model" value="wooden_rail"/>
	<property name="SortOrder2" value="0690"/>  
</block>

<block name="GlideCatwalkRailingCNR">
	<property name="Extends" value="GlideMaster"/>
	<property name="CustomIcon" value="woodCatwalkRailingCNR"/>
	<property name="CreativeMode" value="Dev"/>
	<property name="Model" value="catwalk_corner"/>
	<property name="SortOrder2" value="0660"/>  
</block>

<block name="GlideWedgeRailing">
	<property name="Extends" value="GlideMaster"/>
	<property name="CustomIcon" value="woodCatwalkWedgeRailing"/>
	<property name="CreativeMode" value="Dev"/>
	<property name="Model" value="catwalk_wedge_rail"/>
	<property name="SortOrder2" value="0680"/>  
</block>

<block name="GlideCatwalkWedge">
	<property name="Extends" value="GlideMaster"/>
	<property name="CustomIcon" value="woodCatwalkWedge"/>
	<property name="CreativeMode" value="Dev"/>
	<property name="Model" value="catwalk_wedge"/>
	<property name="SortOrder2" value="0670"/>  
</block>

<block name="GlideBoardRailing">
	<property name="Extends" value="GlideMaster"/>
	<property name="DisplayType" value="blockMulti"/>
	<property name="MultiBlockDim" value="1,2,1"/>
	<property name="Class" value="Stairs"/>
	<property name="CustomIcon" value="woodStairsBoardRailing"/>
	<property name="CreativeMode" value="Dev"/>
	<property name="Shape" value="New"/>
	<property name="Model" value="stairs_railing"/>
	<property name="LightOpacity" value="6"/>
	<property name="ImposterExchange" value="imposterPlate" param1="67"/>
	<property name="UseGlobalUV" value="Local"/>
	<property name="Place" value="TowardsPlacerInverted"/>
	<property name="Collide" value="movement,melee,bullet,arrow,rocket"/>
	<property name="SortOrder2" value="0620"/>  
</block>


	</append>
</configs>